odoo/addons/account_fiscal_year_auto_create/README.rst
odoo/addons/account_fiscal_year_auto_create/__init__.py
odoo/addons/account_fiscal_year_auto_create/__manifest__.py
odoo/addons/account_fiscal_year_auto_create/data/ir_cron.xml
odoo/addons/account_fiscal_year_auto_create/i18n/account_fiscal_year_auto_create.pot
odoo/addons/account_fiscal_year_auto_create/i18n/fr.po
odoo/addons/account_fiscal_year_auto_create/l18n/fr.po
odoo/addons/account_fiscal_year_auto_create/models/__init__.py
odoo/addons/account_fiscal_year_auto_create/models/account_fiscal_year.py
odoo/addons/account_fiscal_year_auto_create/readme/CONTRIBUTORS.rst
odoo/addons/account_fiscal_year_auto_create/readme/DESCRIPTION.rst
odoo/addons/account_fiscal_year_auto_create/static/description/icon.png
odoo/addons/account_fiscal_year_auto_create/static/description/index.html
odoo/addons/account_fiscal_year_auto_create/tests/__init__.py
odoo/addons/account_fiscal_year_auto_create/tests/test_module.py
odoo12_addon_account_fiscal_year_auto_create-12.0.1.0.1.99.dev8.dist-info/METADATA
odoo12_addon_account_fiscal_year_auto_create-12.0.1.0.1.99.dev8.dist-info/WHEEL
odoo12_addon_account_fiscal_year_auto_create-12.0.1.0.1.99.dev8.dist-info/top_level.txt
odoo12_addon_account_fiscal_year_auto_create-12.0.1.0.1.99.dev8.dist-info/RECORD
