Metadata-Version: 2.1
Name: odoo12-addon-account-fiscal-year-auto-create
Version: 12.0.1.0.1.99.dev8
Summary: Automatically create new fiscal years, based on the datas of the last fiscal years
Home-page: https://github.com/OCA/account-financial-tools
Author: GRAP,Odoo Community Association (OCA)
Author-email: support@odoo-community.org
License: AGPL-3
Platform: UNKNOWN
Classifier: Programming Language :: Python
Classifier: Framework :: Odoo
Classifier: Framework :: Odoo :: 12.0
Classifier: License :: OSI Approved :: GNU Affero General Public License v3
Requires-Python: >=3.5
Requires-Dist: odoo <12.1dev,>=12.0a
